{
  "setting": {},
  "condition": {
    "plugin": {
      "list": []
    },
    "game": {
      "list": []
    },
    "gamePlugin": {
      "list": []
    },
    "miniprogram": {
      "list": [
        {
          "name": "报表",
          "pathName": "pages/dashboard/index",
          "query": "",
          "scene": null
        },
        {
          "name": "首页",
          "pathName": "pages/index/index",
          "query": "",
          "scene": null
        },
        {
          "name": "新手引导",
          "pathName": "pages/guide/guidingProcess/index",
          "query": "",
          "scene": null
        },
        {
          "name": "目标",
          "pathName": "pages/target/index",
          "query": "",
          "scene": null,
          "launchMode": "default"
        }
      ]
    }
  }
}